README.md
setup.py
mozart_framework/DatabaseDriver.py
mozart_framework/EmailDriver.py
mozart_framework/ExcelDriver.py
mozart_framework/FileFolderDriver.py
mozart_framework/JamesDriver.py
mozart_framework/LogDriver.py
mozart_framework/OcrSpaceDriver.py
mozart_framework/PDFDriver.py
mozart_framework/QueueItem.py
mozart_framework/ScreenshotDriver.py
mozart_framework/UIDriver.py
mozart_framework/WebDriver.py
mozart_framework/__init__.py
mozart_framework.egg-info/PKG-INFO
mozart_framework.egg-info/SOURCES.txt
mozart_framework.egg-info/dependency_links.txt
mozart_framework.egg-info/requires.txt
mozart_framework.egg-info/top_level.txt